statum/LLMs/LLM.py
statum/LLMs/__init__.py
statum/LLMs/openai_function.py
statum/actions/__init__.py
statum/actions/actions.py
statum/agents/__init__.py
statum/agents/agent.py
statum/agents/chain.py
statum-0.1.1.dev0.dist-info/LICENSE
statum-0.1.1.dev0.dist-info/METADATA
statum-0.1.1.dev0.dist-info/WHEEL
statum-0.1.1.dev0.dist-info/RECORD
